among_us_parser/__init__.py
among_us_parser/live_capture.py
among_us_parser/network_parser.py
among_us_parser/util.py
among_us_parser-0.0.2.dist-info/LICENSE
among_us_parser-0.0.2.dist-info/METADATA
among_us_parser-0.0.2.dist-info/WHEEL
among_us_parser-0.0.2.dist-info/top_level.txt
among_us_parser-0.0.2.dist-info/RECORD
