Metadata-Version: 2.1
Name: among-us-parser
Version: 0.0.2
Summary: A parser for the game among us, that the games network packets
Home-page: https://github.com/RedstoneMedia/among-us-parser-python
Author: RedstoneMedia
License: GNU General Public License v3.0
Keywords: parser network packets among-us AmongUs
Platform: UNKNOWN
Requires-Dist: python-pcapng (>=1.0)
